{
  "form": [
    {
      "firstName": "Lucas",
      "lastName": "Moreira",
      "email": "Roberto.Oliveira97@gmail.com",
      "age": "85",
      "salary": "8178",
      "department": "Ferramentas"
    },
    {
      "firstName": "Isabella",
      "lastName": "Albuquerque",
      "email": "Caua_Nogueira@live.com",
      "age": "52",
      "salary": "6125",
      "department": "Industrial"
    },
    {
      "firstName": "Isabela",
      "lastName": "Silva",
      "email": "Tertuliano64@bol.com.br",
      "age": "43",
      "salary": "8498",
      "department": "Eletrônicos"
    },
    {
      "firstName": "Maria Cecília",
      "lastName": "Franco",
      "email": "Silvia63@bol.com.br",
      "age": "82",
      "salary": "6572",
      "department": "Filmes"
    },
    {
      "firstName": "Helena",
      "lastName": "Barros",
      "email": "Noah.Melo59@yahoo.com",
      "age": "32",
      "salary": "6442",
      "department": "Beleza"
    },
    {
      "firstName": "Carlos",
      "lastName": "Santos",
      "email": "Yago24@gmail.com",
      "age": "84",
      "salary": "6772",
      "department": "Jardim"
    },
    {
      "firstName": "Sílvia",
      "lastName": "Costa",
      "email": "Daniel91@yahoo.com",
      "age": "60",
      "salary": "6268",
      "department": "Jardim"
    },
    {
      "firstName": "Bruna",
      "lastName": "Moreira",
      "email": "Daniel88@gmail.com",
      "age": "74",
      "salary": "3321",
      "department": "Jóias"
    },
    {
      "firstName": "Janaína",
      "lastName": "Moraes",
      "email": "Lorena58@hotmail.com",
      "age": "49",
      "salary": "6902",
      "department": "Turismo"
    },
    {
      "firstName": "Davi",
      "lastName": "Reis",
      "email": "Ladislau31@hotmail.com",
      "age": "53",
      "salary": "5788",
      "department": "Turismo"
    },
    {
      "firstName": "Nicolas",
      "lastName": "Albuquerque",
      "email": "DaviLucca88@hotmail.com",
      "age": "67",
      "salary": "9668",
      "department": "Jogos"
    },
    {
      "firstName": "Carla",
      "lastName": "Macedo",
      "email": "Norberto27@live.com",
      "age": "80",
      "salary": "3650",
      "department": "Mercearia"
    }
  ]
}