{
  "form": [
    {
      "firstName": "Benjamin",
      "lastName": "Pereira",
      "email": "Clara56@hotmail.com",
      "age": "55",
      "salary": "8546",
      "department": "Jóias"
    },
    {
      "firstName": "Isis",
      "lastName": "Xavier",
      "email": "Margarida_Nogueira9@gmail.com",
      "age": "2",
      "salary": "7895",
      "department": "Eletrônicos"
    },
    {
      "firstName": "Caio",
      "lastName": "Costa",
      "email": "Gael90@live.com",
      "age": "74",
      "salary": "9693",
      "department": "Jardim"
    },
    {
      "firstName": "Gabriel",
      "lastName": "Reis",
      "email": "Yango26@bol.com.br",
      "age": "47",
      "salary": "4857",
      "department": "Turismo"
    },
    {
      "firstName": "João",
      "lastName": "Moreira",
      "email": "Calebe.Franco82@bol.com.br",
      "age": "12",
      "salary": "4902",
      "department": "Brinquedos"
    },
    {
      "firstName": "Márcia",
      "lastName": "Carvalho",
      "email": "Elisio51@bol.com.br",
      "age": "98",
      "salary": "6668",
      "department": "Beleza"
    },
    {
      "firstName": "Beatriz",
      "lastName": "Saraiva",
      "email": "Cesar32@live.com",
      "age": "43",
      "salary": "6347",
      "department": "Livros"
    },
    {
      "firstName": "Lívia",
      "lastName": "Xavier",
      "email": "Davi.Silva42@yahoo.com",
      "age": "94",
      "salary": "3642",
      "department": "Ferramentas"
    },
    {
      "firstName": "Sirineu",
      "lastName": "Oliveira",
      "email": "Mercia.Franco81@hotmail.com",
      "age": "36",
      "salary": "6182",
      "department": "Beleza"
    },
    {
      "firstName": "Elisa",
      "lastName": "Braga",
      "email": "MariaCecilia_Carvalho5@hotmail.com",
      "age": "58",
      "salary": "6291",
      "department": "Ferramentas"
    },
    {
      "firstName": "Marcelo",
      "lastName": "Albuquerque",
      "email": "Washington.Silva83@hotmail.com",
      "age": "39",
      "salary": "9436",
      "department": "Ferramentas"
    },
    {
      "firstName": "Benjamin",
      "lastName": "Reis",
      "email": "Theo_Oliveira73@hotmail.com",
      "age": "8",
      "salary": "3209",
      "department": "Mercearia"
    }
  ]
}